{
    "chart": {
        "result": [
            {
                "meta": {
                    "currency": "USD",
                    "symbol": "PX",
                    "exchangeName": "NYQ",
                    "instrumentType": "EQUITY",
                    "firstTradeDate": 1634823000,
                    "regularMarketTime": 1670861543,
                    "gmtoffset": -18000,
                    "timezone": "EST",
                    "exchangeTimezoneName": "America/New_York",
                    "regularMarketPrice": 10.61,
                    "chartPreviousClose": 12.08,
                    "priceHint": 2,
                    "currentTradingPeriod": {
                        "pre": {
                            "timezone": "EST",
                            "start": 1670835600,
                            "end": 1670855400,
                            "gmtoffset": -18000
                        },
                        "regular": {
                            "timezone": "EST",
                            "start": 1670855400,
                            "end": 1670878800,
                            "gmtoffset": -18000
                        },
                        "post": {
                            "timezone": "EST",
                            "start": 1670878800,
                            "end": 1670893200,
                            "gmtoffset": -18000
                        }
                    },
                    "dataGranularity": "1d",
                    "range": "",
                    "validRanges": [
                        "1d",
                        "5d",
                        "1mo",
                        "3mo",
                        "6mo",
                        "1y",
                        "2y",
                        "ytd",
                        "max"
                    ]
                },
                "timestamp": [
                    1634823000,
                    1634909400,
                    1635168600,
                    1635255000,
                    1635341400,
                    1635427800,
                    1635514200,
                    1635773400,
                    1635859800,
                    1635946200,
                    1636032600,
                    1636119000,
                    1636381800,
                    1636468200,
                    1636554600,
                    1636641000,
                    1636727400,
                    1636986600,
                    1637073000,
                    1637159400,
                    1637245800,
                    1637332200,
                    1637591400,
                    1637677800,
                    1637764200,
                    1637937000,
                    1638196200,
                    1638282600,
                    1638369000,
                    1638455400,
                    1638541800,
                    1638801000,
                    1638887400,
                    1638973800,
                    1639060200,
                    1639146600,
                    1639405800,
                    1639492200,
                    1639578600,
                    1639665000,
                    1639751400,
                    1640010600,
                    1640097000,
                    1640183400,
                    1640269800,
                    1640615400,
                    1640701800,
                    1640788200,
                    1640874600,
                    1640961000,
                    1641220200,
                    1641306600,
                    1641393000,
                    1641479400,
                    1641565800,
                    1641825000,
                    1641911400,
                    1641997800,
                    1642084200,
                    1642170600,
                    1642516200,
                    1642602600,
                    1642689000,
                    1642775400,
                    1643034600,
                    1643121000,
                    1643207400,
                    1643293800,
                    1643380200,
                    1643639400,
                    1643725800,
                    1643812200,
                    1643898600,
                    1643985000,
                    1644244200,
                    1644330600,
                    1644417000,
                    1644503400,
                    1644589800,
                    1644849000,
                    1644935400,
                    1645021800,
                    1645108200,
                    1645194600,
                    1645540200,
                    1645626600,
                    1645713000,
                    1645799400,
                    1646058600,
                    1646145000,
                    1646231400,
                    1646317800,
                    1646404200,
                    1646663400,
                    1646749800,
                    1646836200,
                    1646922600,
                    1647009000,
                    1647264600,
                    1647351000,
                    1647437400,
                    1647523800,
                    1647610200,
                    1647869400,
                    1647955800,
                    1648042200,
                    1648128600,
                    1648215000,
                    1648474200,
                    1648560600,
                    1648647000,
                    1648733400,
                    1648819800,
                    1649079000,
                    1649165400,
                    1649251800,
                    1649338200,
                    1649424600,
                    1649683800,
                    1649770200,
                    1649856600,
                    1649943000,
                    1650288600,
                    1650375000,
                    1650461400,
                    1650547800,
                    1650634200,
                    1650893400,
                    1650979800,
                    1651066200,
                    1651152600,
                    1651239000,
                    1651498200,
                    1651584600,
                    1651671000,
                    1651757400,
                    1651843800,
                    1652103000,
                    1652189400,
                    1652275800,
                    1652362200,
                    1652448600,
                    1652707800,
                    1652794200,
                    1652880600,
                    1652967000,
                    1653053400,
                    1653312600,
                    1653399000,
                    1653485400,
                    1653571800,
                    1653658200,
                    1654003800,
                    1654090200,
                    1654176600,
                    1654263000,
                    1654522200,
                    1654608600,
                    1654695000,
                    1654781400,
                    1654867800,
                    1655127000,
                    1655213400,
                    1655299800,
                    1655386200,
                    1655472600,
                    1655818200,
                    1655904600,
                    1655991000,
                    1656077400,
                    1656336600,
                    1656423000,
                    1656509400,
                    1656595800,
                    1656682200,
                    1657027800,
                    1657114200,
                    1657200600,
                    1657287000,
                    1657546200,
                    1657632600,
                    1657719000,
                    1657805400,
                    1657891800,
                    1658151000,
                    1658237400,
                    1658323800,
                    1658410200,
                    1658496600,
                    1658755800,
                    1658842200,
                    1658928600,
                    1659015000,
                    1659101400,
                    1659360600,
                    1659447000,
                    1659533400,
                    1659619800,
                    1659706200,
                    1659965400,
                    1660051800,
                    1660138200,
                    1660224600,
                    1660311000,
                    1660570200,
                    1660656600,
                    1660743000,
                    1660829400,
                    1660915800,
                    1661175000,
                    1661261400,
                    1661347800,
                    1661434200,
                    1661520600,
                    1661779800,
                    1661866200,
                    1661952600,
                    1662039000,
                    1662125400,
                    1662471000,
                    1662557400,
                    1662643800,
                    1662730200,
                    1662989400,
                    1663075800,
                    1663162200,
                    1663248600,
                    1663335000,
                    1663594200,
                    1663680600,
                    1663767000,
                    1663853400,
                    1663939800,
                    1664199000,
                    1664285400,
                    1664371800,
                    1664458200,
                    1664544600,
                    1664803800,
                    1664890200,
                    1664976600,
                    1665063000,
                    1665149400,
                    1665408600,
                    1665495000,
                    1665581400,
                    1665667800,
                    1665754200,
                    1666013400,
                    1666099800,
                    1666186200,
                    1666272600,
                    1666359000,
                    1666618200,
                    1666704600,
                    1666791000,
                    1666877400,
                    1666963800,
                    1667223000,
                    1667309400,
                    1667395800,
                    1667482200,
                    1667568600,
                    1667831400,
                    1667917800,
                    1668004200,
                    1668090600,
                    1668177000,
                    1668436200,
                    1668522600,
                    1668609000,
                    1668695400,
                    1668781800,
                    1669041000,
                    1669127400,
                    1669213800,
                    1669386600,
                    1669645800,
                    1669732200,
                    1669818600,
                    1669905000,
                    1669991400,
                    1670250600,
                    1670337000,
                    1670423400,
                    1670509800,
                    1670596200,
                    1670861543
                ],
                "events": {
                    "dividends": {
                        "1653658200": {
                            "amount": 0.03,
                            "date": 1653658200
                        },
                        "1661520600": {
                            "amount": 0.03,
                            "date": 1661520600
                        },
                        "1669732200": {
                            "amount": 0.03,
                            "date": 1669732200
                        }
                    }
                },
                "indicators": {
                    "quote": [
                        {
                            "open": [
                                12.020000457763672,
                                12.0,
                                12.010000228881836,
                                12.5,
                                12.350000381469727,
                                12.420000076293945,
                                12.119999885559082,
                                12.390000343322754,
                                12.050000190734863,
                                12.180000305175781,
                                12.050000190734863,
                                12.220000267028809,
                                12.359999656677246,
                                12.319999694824219,
                                12.359999656677246,
                                12.3100004196167,
                                12.630000114440918,
                                13.850000381469727,
                                13.989999771118164,
                                14.010000228881836,
                                13.930000305175781,
                                13.90999984741211,
                                14.680000305175781,
                                13.899999618530273,
                                13.100000381469727,
                                13.319999694824219,
                                13.40999984741211,
                                13.220000267028809,
                                13.880000114440918,
                                14.180000305175781,
                                14.399999618530273,
                                14.5,
                                14.510000228881836,
                                15.010000228881836,
                                14.539999961853027,
                                14.449999809265137,
                                13.989999771118164,
                                13.239999771118164,
                                13.260000228881836,
                                13.420000076293945,
                                12.960000038146973,
                                12.15999984741211,
                                12.199999809265137,
                                12.279999732971191,
                                12.430000305175781,
                                12.6899995803833,
                                12.609999656677246,
                                12.760000228881836,
                                13.180000305175781,
                                13.550000190734863,
                                14.109999656677246,
                                13.670000076293945,
                                13.359999656677246,
                                13.149999618530273,
                                13.0600004196167,
                                13.069999694824219,
                                12.670000076293945,
                                13.0600004196167,
                                13.15999984741211,
                                13.390000343322754,
                                13.119999885559082,
                                12.84000015258789,
                                12.829999923706055,
                                12.550000190734863,
                                12.100000381469727,
                                12.0,
                                12.100000381469727,
                                11.789999961853027,
                                11.710000038146973,
                                12.119999885559082,
                                12.119999885559082,
                                12.720000267028809,
                                12.600000381469727,
                                12.550000190734863,
                                12.720000267028809,
                                12.600000381469727,
                                12.630000114440918,
                                12.5,
                                12.5,
                                12.5600004196167,
                                12.3100004196167,
                                12.720000267028809,
                                13.279999732971191,
                                13.069999694824219,
                                12.65999984741211,
                                12.359999656677246,
                                12.289999961853027,
                                12.380000114440918,
                                12.399999618530273,
                                12.609999656677246,
                                11.9399995803833,
                                12.270000457763672,
                                12.069999694824219,
                                12.020000457763672,
                                12.0,
                                11.970000267028809,
                                11.989999771118164,
                                11.90999984741211,
                                11.649999618530273,
                                11.760000228881836,
                                11.869999885559082,
                                12.0,
                                12.170000076293945,
                                11.970000267028809,
                                12.170000076293945,
                                12.239999771118164,
                                12.399999618530273,
                                12.319999694824219,
                                12.390000343322754,
                                12.390000343322754,
                                12.170000076293945,
                                12.1899995803833,
                                12.119999885559082,
                                12.279999732971191,
                                12.329999923706055,
                                11.8100004196167,
                                11.25,
                                11.449999809265137,
                                11.680000305175781,
                                11.4399995803833,
                                11.3100004196167,
                                11.890000343322754,
                                11.59000015258789,
                                11.34000015258789,
                                11.890000343322754,
                                12.199999809265137,
                                11.789999961853027,
                                11.850000381469727,
                                12.15999984741211,
                                12.260000228881836,
                                12.149999618530273,
                                12.199999809265137,
                                12.100000381469727,
                                12.289999961853027,
                                12.15999984741211,
                                12.300000190734863,
                                12.140000343322754,
                                12.109999656677246,
                                11.380000114440918,
                                10.770000457763672,
                                10.8100004196167,
                                11.34000015258789,
                                11.210000038146973,
                                11.470000267028809,
                                11.329999923706055,
                                11.40999984741211,
                                11.329999923706055,
                                11.380000114440918,
                                11.380000114440918,
                                11.300000190734863,
                                11.300000190734863,
                                11.760000228881836,
                                11.649999618530273,
                                11.59000015258789,
                                11.550000190734863,
                                11.800000190734863,
                                12.119999885559082,
                                11.399999618530273,
                                11.59000015258789,
                                11.260000228881836,
                                11.140000343322754,
                                10.300000190734863,
                                10.3100004196167,
                                10.5600004196167,
                                10.619999885559082,
                                10.569999694824219,
                                10.90999984741211,
                                10.770000457763672,
                                10.5,
                                10.5,
                                10.640000343322754,
                                11.010000228881836,
                                11.239999771118164,
                                10.789999961853027,
                                11.09000015258789,
                                11.229999542236328,
                                11.779999732971191,
                                11.850000381469727,
                                12.100000381469727,
                                11.899999618530273,
                                11.770000457763672,
                                11.739999771118164,
                                11.380000114440918,
                                11.600000381469727,
                                12.0600004196167,
                                12.010000228881836,
                                11.850000381469727,
                                11.920000076293945,
                                11.859999656677246,
                                11.649999618530273,
                                11.59000015258789,
                                11.59000015258789,
                                11.770000457763672,
                                11.829999923706055,
                                11.829999923706055,
                                12.180000305175781,
                                11.949999809265137,
                                12.199999809265137,
                                12.180000305175781,
                                12.1899995803833,
                                12.210000038146973,
                                12.25,
                                12.489999771118164,
                                12.59000015258789,
                                13.520000457763672,
                                13.109999656677246,
                                13.010000228881836,
                                13.170000076293945,
                                13.34000015258789,
                                12.890000343322754,
                                12.859999656677246,
                                12.600000381469727,
                                12.75,
                                12.970000267028809,
                                12.949999809265137,
                                12.850000381469727,
                                12.84000015258789,
                                12.460000038146973,
                                12.319999694824219,
                                12.170000076293945,
                                11.619999885559082,
                                12.039999961853027,
                                11.970000267028809,
                                11.989999771118164,
                                11.84000015258789,
                                11.579999923706055,
                                11.569999694824219,
                                11.369999885559082,
                                11.359999656677246,
                                11.270000457763672,
                                11.119999885559082,
                                11.229999542236328,
                                10.680000305175781,
                                10.699999809265137,
                                10.789999961853027,
                                10.550000190734863,
                                10.479999542236328,
                                10.380000114440918,
                                10.5,
                                10.880000114440918,
                                10.850000381469727,
                                10.949999809265137,
                                10.819999694824219,
                                10.630000114440918,
                                10.40999984741211,
                                10.220000267028809,
                                10.010000228881836,
                                10.479999542236328,
                                10.449999809265137,
                                10.529999732971191,
                                10.430000305175781,
                                10.420000076293945,
                                10.260000228881836,
                                10.489999771118164,
                                10.600000381469727,
                                10.8100004196167,
                                10.710000038146973,
                                10.680000305175781,
                                10.729999542236328,
                                10.4399995803833,
                                10.550000190734863,
                                10.40999984741211,
                                10.260000228881836,
                                10.109999656677246,
                                10.050000190734863,
                                9.800000190734863,
                                10.119999885559082,
                                10.470000267028809,
                                10.279999732971191,
                                9.84000015258789,
                                9.90999984741211,
                                9.739999771118164,
                                10.0,
                                10.1899995803833,
                                10.15999984741211,
                                10.369999885559082,
                                10.229999542236328,
                                10.369999885559082,
                                10.229999542236328,
                                10.239999771118164,
                                10.220000267028809,
                                10.359999656677246,
                                10.550000190734863,
                                10.479999542236328,
                                10.239999771118164,
                                10.300000190734863,
                                10.25,
                                10.359999656677246
                            ],
                            "high": [
                                12.699999809265137,
                                12.100000381469727,
                                12.6899995803833,
                                12.699999809265137,
                                13.154999732971191,
                                12.579999923706055,
                                12.720000267028809,
                                12.720000267028809,
                                12.479999542236328,
                                12.649999618530273,
                                12.5,
                                12.600000381469727,
                                12.600000381469727,
                                12.600000381469727,
                                12.789999961853027,
                                12.75,
                                14.0,
                                14.670000076293945,
                                14.479999542236328,
                                14.27299976348877,
                                14.390000343322754,
                                14.244999885559082,
                                14.949999809265137,
                                13.899999618530273,
                                13.529999732971191,
                                13.369999885559082,
                                13.40999984741211,
                                13.800000190734863,
                                14.300000190734863,
                                14.380000114440918,
                                14.600000381469727,
                                14.899999618530273,
                                15.29699993133545,
                                15.029999732971191,
                                14.847000122070312,
                                14.600000381469727,
                                14.1899995803833,
                                13.699999809265137,
                                13.920000076293945,
                                13.6899995803833,
                                13.539999961853027,
                                12.720000267028809,
                                12.539999961853027,
                                12.5600004196167,
                                12.800000190734863,
                                12.920000076293945,
                                12.829999923706055,
                                13.350000381469727,
                                13.609999656677246,
                                14.029999732971191,
                                14.1899995803833,
                                13.680000305175781,
                                13.600000381469727,
                                13.335000038146973,
                                13.199999809265137,
                                13.069999694824219,
                                13.140000343322754,
                                13.4399995803833,
                                13.680000305175781,
                                13.470000267028809,
                                13.270000457763672,
                                13.185999870300293,
                                12.84000015258789,
                                12.680000305175781,
                                12.387999534606934,
                                12.149999618530273,
                                12.166999816894531,
                                11.869999885559082,
                                11.868000030517578,
                                12.149999618530273,
                                12.630000114440918,
                                12.819999694824219,
                                12.699999809265137,
                                12.802000045776367,
                                12.821999549865723,
                                12.75,
                                12.680000305175781,
                                12.640000343322754,
                                12.609999656677246,
                                12.600000381469727,
                                12.75,
                                13.5600004196167,
                                13.420000076293945,
                                13.100000381469727,
                                12.739999771118164,
                                12.859999656677246,
                                12.529999732971191,
                                12.539999961853027,
                                12.567999839782715,
                                13.720000267028809,
                                12.489999771118164,
                                12.574999809265137,
                                12.100000381469727,
                                12.680000305175781,
                                12.1899995803833,
                                12.220000267028809,
                                12.149999618530273,
                                11.960000038146973,
                                11.890000343322754,
                                11.890000343322754,
                                12.210000038146973,
                                12.289999961853027,
                                12.479999542236328,
                                12.260000228881836,
                                12.3100004196167,
                                12.600000381469727,
                                12.529999732971191,
                                12.5,
                                12.449999809265137,
                                12.579999923706055,
                                12.4399995803833,
                                12.300000190734863,
                                12.420000076293945,
                                12.539999961853027,
                                12.359999656677246,
                                11.8100004196167,
                                11.619999885559082,
                                11.8100004196167,
                                11.859000205993652,
                                11.619999885559082,
                                11.8100004196167,
                                11.989999771118164,
                                11.680000305175781,
                                11.8100004196167,
                                12.210000038146973,
                                12.489999771118164,
                                12.0600004196167,
                                12.300000190734863,
                                12.59000015258789,
                                12.4399995803833,
                                12.390000343322754,
                                12.430000305175781,
                                12.270000457763672,
                                12.289999961853027,
                                12.460000038146973,
                                12.319999694824219,
                                12.300000190734863,
                                12.220000267028809,
                                11.569999694824219,
                                11.109999656677246,
                                11.305000305175781,
                                11.449999809265137,
                                11.4399995803833,
                                11.545000076293945,
                                11.59000015258789,
                                11.65999984741211,
                                11.420000076293945,
                                11.680000305175781,
                                11.420000076293945,
                                11.399999618530273,
                                11.869999885559082,
                                12.100000381469727,
                                11.649999618530273,
                                11.699999809265137,
                                11.899999618530273,
                                12.0,
                                12.260000228881836,
                                11.619999885559082,
                                11.649999618530273,
                                11.40999984741211,
                                11.199999809265137,
                                10.479999542236328,
                                10.510000228881836,
                                11.039999961853027,
                                10.670000076293945,
                                10.9399995803833,
                                11.300000190734863,
                                10.9399995803833,
                                10.6899995803833,
                                10.873000144958496,
                                11.050000190734863,
                                11.260000228881836,
                                11.239999771118164,
                                11.119999885559082,
                                11.4399995803833,
                                11.859999656677246,
                                11.850000381469727,
                                12.15999984741211,
                                12.100000381469727,
                                11.899999618530273,
                                12.050000190734863,
                                11.789999961853027,
                                11.479999542236328,
                                11.930000305175781,
                                12.100000381469727,
                                12.178999900817871,
                                12.029999732971191,
                                12.015000343322754,
                                11.859999656677246,
                                11.649999618530273,
                                11.59000015258789,
                                11.720000267028809,
                                11.899999618530273,
                                11.930000305175781,
                                12.229999542236328,
                                12.229999542236328,
                                12.239999771118164,
                                12.289999961853027,
                                12.329999923706055,
                                12.34000015258789,
                                12.229999542236328,
                                12.399999618530273,
                                12.600000381469727,
                                13.550000190734863,
                                13.779999732971191,
                                13.430000305175781,
                                13.229999542236328,
                                13.399999618530273,
                                13.34000015258789,
                                12.930000305175781,
                                12.930000305175781,
                                12.774999618530273,
                                12.90999984741211,
                                13.260000228881836,
                                13.1850004196167,
                                12.920000076293945,
                                12.979999542236328,
                                12.569999694824219,
                                12.510000228881836,
                                12.305000305175781,
                                12.180000305175781,
                                12.140000343322754,
                                12.079999923706055,
                                12.180000305175781,
                                11.949999809265137,
                                11.880000114440918,
                                11.739999771118164,
                                11.4399995803833,
                                11.430000305175781,
                                11.270000457763672,
                                11.430000305175781,
                                11.229999542236328,
                                10.704999923706055,
                                10.869999885559082,
                                10.819999694824219,
                                10.699999809265137,
                                10.539999961853027,
                                10.550000190734863,
                                10.779999732971191,
                                11.057999610900879,
                                11.0600004196167,
                                11.086999893188477,
                                10.869999885559082,
                                10.630000114440918,
                                10.40999984741211,
                                10.369999885559082,
                                10.40999984741211,
                                10.53499984741211,
                                10.489999771118164,
                                10.609999656677246,
                                10.550000190734863,
                                10.729999542236328,
                                10.569999694824219,
                                10.670000076293945,
                                10.899999618530273,
                                10.850000381469727,
                                10.75,
                                10.850000381469727,
                                10.850000381469727,
                                10.550000190734863,
                                10.720000267028809,
                                10.4399995803833,
                                10.359999656677246,
                                10.170000076293945,
                                10.050000190734863,
                                9.899999618530273,
                                10.829999923706055,
                                10.680000305175781,
                                10.289999961853027,
                                10.260000228881836,
                                10.050000190734863,
                                10.104999542236328,
                                10.260000228881836,
                                10.390000343322754,
                                10.350000381469727,
                                10.369999885559082,
                                10.430000305175781,
                                10.399999618530273,
                                10.34000015258789,
                                10.359999656677246,
                                10.510000228881836,
                                10.604999542236328,
                                10.585000038146973,
                                10.520000457763672,
                                10.319999694824219,
                                10.479999542236328,
                                10.359999656677246,
                                10.614999771118164
                            ],
                            "close": [
                                12.079999923706055,
                                12.0,
                                12.5,
                                12.489999771118164,
                                12.350000381469727,
                                12.210000038146973,
                                12.5,
                                12.149999618530273,
                                12.319999694824219,
                                12.25,
                                12.420000076293945,
                                12.5,
                                12.489999771118164,
                                12.569999694824219,
                                12.550000190734863,
                                12.649999618530273,
                                13.449999809265137,
                                13.989999771118164,
                                13.960000038146973,
                                13.960000038146973,
                                14.029999732971191,
                                13.949999809265137,
                                13.930000305175781,
                                13.229999542236328,
                                13.5,
                                13.270000457763672,
                                13.170000076293945,
                                13.770000457763672,
                                14.020000457763672,
                                14.350000381469727,
                                14.350000381469727,
                                14.5,
                                15.010000228881836,
                                14.729999542236328,
                                14.380000114440918,
                                14.029999732971191,
                                13.489999771118164,
                                13.25,
                                13.430000305175781,
                                13.029999732971191,
                                12.710000038146973,
                                12.140000343322754,
                                12.300000190734863,
                                12.420000076293945,
                                12.600000381469727,
                                12.649999618530273,
                                12.739999771118164,
                                13.149999618530273,
                                13.539999961853027,
                                13.979999542236328,
                                13.670000076293945,
                                13.430000305175781,
                                13.199999809265137,
                                13.069999694824219,
                                13.100000381469727,
                                12.739999771118164,
                                13.0,
                                13.149999618530273,
                                13.5,
                                13.300000190734863,
                                12.800000190734863,
                                12.720000267028809,
                                12.630000114440918,
                                12.25,
                                12.100000381469727,
                                12.020000457763672,
                                11.670000076293945,
                                11.710000038146973,
                                11.789999961853027,
                                12.079999923706055,
                                12.569999694824219,
                                12.699999809265137,
                                12.510000228881836,
                                12.65999984741211,
                                12.600000381469727,
                                12.550000190734863,
                                12.569999694824219,
                                12.5,
                                12.529999732971191,
                                12.210000038146973,
                                12.75,
                                13.3100004196167,
                                13.050000190734863,
                                12.819999694824219,
                                12.260000228881836,
                                12.609999656677246,
                                12.300000190734863,
                                12.479999542236328,
                                12.4399995803833,
                                11.90999984741211,
                                12.300000190734863,
                                12.15999984741211,
                                12.09000015258789,
                                12.0,
                                11.800000190734863,
                                12.199999809265137,
                                11.890000343322754,
                                11.699999809265137,
                                11.670000076293945,
                                11.829999923706055,
                                11.970000267028809,
                                12.220000267028809,
                                11.899999618530273,
                                12.109999656677246,
                                12.279999732971191,
                                12.279999732971191,
                                12.399999618530273,
                                12.399999618530273,
                                12.359999656677246,
                                12.170000076293945,
                                12.170000076293945,
                                12.119999885559082,
                                12.279999732971191,
                                12.380000114440918,
                                11.890000343322754,
                                11.380000114440918,
                                11.510000228881836,
                                11.5600004196167,
                                11.4399995803833,
                                11.390000343322754,
                                11.8100004196167,
                                11.699999809265137,
                                11.420000076293945,
                                11.789999961853027,
                                12.130000114440918,
                                11.850000381469727,
                                11.899999618530273,
                                12.220000267028809,
                                12.210000038146973,
                                12.09000015258789,
                                12.25,
                                12.100000381469727,
                                12.239999771118164,
                                12.15999984741211,
                                12.460000038146973,
                                12.1899995803833,
                                12.260000228881836,
                                11.34000015258789,
                                10.75,
                                10.859999656677246,
                                11.039999961853027,
                                11.199999809265137,
                                11.260000228881836,
                                11.40999984741211,
                                11.510000228881836,
                                11.180000305175781,
                                11.390000343322754,
                                11.489999771118164,
                                11.289999961853027,
                                11.220000267028809,
                                11.680000305175781,
                                11.65999984741211,
                                11.5,
                                11.449999809265137,
                                11.850000381469727,
                                11.989999771118164,
                                11.420000076293945,
                                11.550000190734863,
                                11.239999771118164,
                                11.270000457763672,
                                10.5600004196167,
                                10.239999771118164,
                                10.430000305175781,
                                10.90999984741211,
                                10.539999961853027,
                                10.890000343322754,
                                10.989999771118164,
                                10.59000015258789,
                                10.40999984741211,
                                10.5600004196167,
                                10.890000343322754,
                                11.260000228881836,
                                10.970000267028809,
                                11.119999885559082,
                                11.420000076293945,
                                11.859999656677246,
                                11.75,
                                12.0600004196167,
                                11.90999984741211,
                                11.75,
                                11.850000381469727,
                                11.5,
                                11.449999809265137,
                                11.930000305175781,
                                11.970000267028809,
                                11.90999984741211,
                                11.899999618530273,
                                11.90999984741211,
                                11.699999809265137,
                                11.529999732971191,
                                11.5,
                                11.6899995803833,
                                11.770000457763672,
                                11.829999923706055,
                                12.1899995803833,
                                12.010000228881836,
                                12.220000267028809,
                                12.229999542236328,
                                12.109999656677246,
                                12.140000343322754,
                                12.210000038146973,
                                12.369999885559082,
                                12.25,
                                13.399999618530273,
                                13.020000457763672,
                                13.09000015258789,
                                13.1899995803833,
                                13.399999618530273,
                                12.989999771118164,
                                12.789999961853027,
                                12.699999809265137,
                                12.6899995803833,
                                12.699999809265137,
                                12.979999542236328,
                                12.710000038146973,
                                12.470000267028809,
                                12.479999542236328,
                                12.319999694824219,
                                12.270000457763672,
                                11.720000267028809,
                                12.140000343322754,
                                11.899999618530273,
                                11.890000343322754,
                                12.010000228881836,
                                11.569999694824219,
                                11.670000076293945,
                                11.470000267028809,
                                11.430000305175781,
                                11.3100004196167,
                                11.029999732971191,
                                11.25,
                                10.710000038146973,
                                10.609999656677246,
                                10.699999809265137,
                                10.489999771118164,
                                10.609999656677246,
                                10.350000381469727,
                                10.520000457763672,
                                10.710000038146973,
                                11.050000190734863,
                                10.979999542236328,
                                10.880000114440918,
                                10.619999885559082,
                                10.449999809265137,
                                10.270000457763672,
                                10.239999771118164,
                                10.399999618530273,
                                10.329999923706055,
                                10.319999694824219,
                                10.479999542236328,
                                10.430000305175781,
                                10.319999694824219,
                                10.479999542236328,
                                10.600000381469727,
                                10.779999732971191,
                                10.65999984741211,
                                10.619999885559082,
                                10.8100004196167,
                                10.390000343322754,
                                10.479999542236328,
                                10.550000190734863,
                                10.130000114440918,
                                10.020000457763672,
                                10.0,
                                9.880000114440918,
                                9.720000267028809,
                                10.539999961853027,
                                10.279999732971191,
                                9.720000267028809,
                                10.0,
                                9.90999984741211,
                                9.970000267028809,
                                10.25,
                                10.140000343322754,
                                10.279999732971191,
                                10.1899995803833,
                                10.390000343322754,
                                10.25,
                                10.220000267028809,
                                10.229999542236328,
                                10.460000038146973,
                                10.550000190734863,
                                10.529999732971191,
                                10.239999771118164,
                                10.300000190734863,
                                10.300000190734863,
                                10.270000457763672,
                                10.609999656677246
                            ],
                            "volume": [
                                6070400,
                                851700,
                                1119000,
                                682200,
                                330100,
                                331400,
                                384700,
                                491600,
                                93400,
                                191500,
                                121600,
                                85800,
                                267100,
                                209400,
                                334600,
                                167000,
                                563200,
                                389700,
                                284000,
                                209200,
                                372600,
                                176900,
                                329300,
                                449800,
                                75600,
                                31700,
                                274800,
                                334600,
                                298600,
                                472100,
                                365800,
                                416600,
                                228200,
                                188600,
                                145500,
                                145000,
                                174600,
                                161400,
                                461400,
                                570600,
                                1412600,
                                643500,
                                517600,
                                194700,
                                228600,
                                91400,
                                189700,
                                193300,
                                169000,
                                130700,
                                174800,
                                253900,
                                132200,
                                122100,
                                65300,
                                220900,
                                86100,
                                156800,
                                162900,
                                114700,
                                68200,
                                60200,
                                67300,
                                300300,
                                193900,
                                283400,
                                182800,
                                125700,
                                188600,
                                259200,
                                238100,
                                151700,
                                138800,
                                182400,
                                202000,
                                126700,
                                127700,
                                131000,
                                160100,
                                109400,
                                82300,
                                81400,
                                107700,
                                82100,
                                125000,
                                146800,
                                177100,
                                179500,
                                272000,
                                419000,
                                240800,
                                233500,
                                333400,
                                375600,
                                118600,
                                109500,
                                89600,
                                130300,
                                153800,
                                179600,
                                258500,
                                109700,
                                321600,
                                126400,
                                140000,
                                99100,
                                142600,
                                110300,
                                93800,
                                356100,
                                113100,
                                108800,
                                146800,
                                232800,
                                261700,
                                158700,
                                182200,
                                93100,
                                92600,
                                91300,
                                81500,
                                129400,
                                75700,
                                120400,
                                151400,
                                262500,
                                392200,
                                195300,
                                193800,
                                221100,
                                254500,
                                746400,
                                138200,
                                77200,
                                113300,
                                112400,
                                112800,
                                252400,
                                224300,
                                175100,
                                188700,
                                170500,
                                103800,
                                134000,
                                146200,
                                96000,
                                129300,
                                105900,
                                59200,
                                117500,
                                95600,
                                118400,
                                83100,
                                109400,
                                94700,
                                78100,
                                200900,
                                145900,
                                122900,
                                125900,
                                102500,
                                155800,
                                148600,
                                496800,
                                504000,
                                1091600,
                                353200,
                                497900,
                                93000,
                                143000,
                                292400,
                                197600,
                                120300,
                                92000,
                                69200,
                                143000,
                                142500,
                                80900,
                                36700,
                                42300,
                                58500,
                                36200,
                                60300,
                                69300,
                                112200,
                                268300,
                                344000,
                                78600,
                                81000,
                                133400,
                                70500,
                                79300,
                                117300,
                                81100,
                                311700,
                                87700,
                                98700,
                                44000,
                                26300,
                                33100,
                                65100,
                                51200,
                                114000,
                                482300,
                                232200,
                                225000,
                                163000,
                                138200,
                                82500,
                                132900,
                                90800,
                                142900,
                                95300,
                                268500,
                                175700,
                                112100,
                                256600,
                                121100,
                                70900,
                                352100,
                                203800,
                                90400,
                                88500,
                                99600,
                                236100,
                                241700,
                                95700,
                                272400,
                                90900,
                                243000,
                                89400,
                                104500,
                                268100,
                                332700,
                                189400,
                                95900,
                                158400,
                                1020700,
                                166900,
                                92100,
                                53100,
                                43800,
                                55400,
                                96700,
                                249300,
                                96700,
                                146400,
                                147300,
                                160100,
                                143300,
                                134800,
                                254100,
                                64700,
                                86800,
                                261600,
                                54500,
                                73800,
                                76500,
                                84400,
                                171100,
                                75100,
                                54800,
                                132400,
                                143800,
                                84800,
                                97800,
                                240700,
                                244200,
                                219600,
                                153500,
                                149000,
                                142000,
                                176700,
                                117000,
                                163200,
                                150700,
                                53200,
                                107200,
                                91500,
                                213200,
                                109300,
                                125200,
                                181200,
                                171700,
                                87400,
                                145900,
                                108800,
                                23713
                            ],
                            "low": [
                                11.270000457763672,
                                11.710000038146973,
                                12.0,
                                12.010000228881836,
                                12.229999542236328,
                                12.100000381469727,
                                12.100000381469727,
                                12.0,
                                12.050000190734863,
                                12.069999694824219,
                                12.050000190734863,
                                12.220000267028809,
                                12.25,
                                12.3100004196167,
                                12.359999656677246,
                                12.130000114440918,
                                12.630000114440918,
                                13.6899995803833,
                                13.859999656677246,
                                13.800000190734863,
                                13.470000267028809,
                                13.609999656677246,
                                13.920000076293945,
                                12.899999618530273,
                                13.100000381469727,
                                13.126999855041504,
                                12.930000305175781,
                                13.050000190734863,
                                13.859999656677246,
                                13.90999984741211,
                                14.211999893188477,
                                14.100000381469727,
                                14.510000228881836,
                                14.229999542236328,
                                13.859999656677246,
                                13.59000015258789,
                                13.0600004196167,
                                13.029999732971191,
                                13.109999656677246,
                                13.020000457763672,
                                12.329999923706055,
                                12.140000343322754,
                                12.09000015258789,
                                12.279999732971191,
                                12.399999618530273,
                                12.5,
                                12.609999656677246,
                                12.529999732971191,
                                13.069999694824219,
                                13.550000190734863,
                                13.390000343322754,
                                13.119999885559082,
                                13.0,
                                12.8100004196167,
                                12.90999984741211,
                                12.640000343322754,
                                12.670000076293945,
                                12.8100004196167,
                                12.949999809265137,
                                13.0,
                                12.770000457763672,
                                12.699999809265137,
                                12.600000381469727,
                                12.239999771118164,
                                12.029999732971191,
                                11.789999961853027,
                                11.579999923706055,
                                11.430000305175781,
                                11.4399995803833,
                                11.899999618530273,
                                11.850000381469727,
                                12.34000015258789,
                                12.460000038146973,
                                12.442999839782715,
                                12.489999771118164,
                                12.520000457763672,
                                12.470000267028809,
                                12.420000076293945,
                                12.369999885559082,
                                12.130000114440918,
                                12.291000366210938,
                                12.699999809265137,
                                13.050000190734863,
                                12.779999732971191,
                                11.989999771118164,
                                12.199999809265137,
                                11.819999694824219,
                                12.15999984741211,
                                12.149999618530273,
                                11.859999656677246,
                                11.930000305175781,
                                12.050000190734863,
                                11.819999694824219,
                                11.710000038146973,
                                11.739999771118164,
                                11.899999618530273,
                                11.800000190734863,
                                11.619999885559082,
                                11.449999809265137,
                                11.619999885559082,
                                11.765000343322754,
                                12.0,
                                11.899999618530273,
                                11.930000305175781,
                                12.069999694824219,
                                12.15999984741211,
                                12.25,
                                12.319999694824219,
                                12.300000190734863,
                                12.119999885559082,
                                12.095000267028809,
                                12.09000015258789,
                                12.0600004196167,
                                12.149999618530273,
                                11.710000038146973,
                                11.369999885559082,
                                11.119999885559082,
                                11.399999618530273,
                                11.3149995803833,
                                11.270000457763672,
                                11.25,
                                11.5600004196167,
                                11.40999984741211,
                                11.34000015258789,
                                11.880000114440918,
                                11.65999984741211,
                                11.539999961853027,
                                11.850000381469727,
                                11.859999656677246,
                                11.970000267028809,
                                11.979999542236328,
                                11.979999542236328,
                                11.979999542236328,
                                12.123000144958496,
                                12.020000457763672,
                                11.970000267028809,
                                11.899999618530273,
                                11.15999984741211,
                                10.680000305175781,
                                10.529999732971191,
                                10.569999694824219,
                                11.020000457763672,
                                11.109999656677246,
                                11.210000038146973,
                                11.300000190734863,
                                11.050000190734863,
                                11.210000038146973,
                                11.319999694824219,
                                11.029999732971191,
                                11.119999885559082,
                                11.300000190734863,
                                11.619999885559082,
                                11.289999961853027,
                                11.279999732971191,
                                11.470000267028809,
                                11.6899995803833,
                                11.3100004196167,
                                11.282999992370605,
                                10.970000267028809,
                                11.0600004196167,
                                10.5600004196167,
                                10.09000015258789,
                                10.15999984741211,
                                10.430000305175781,
                                10.270000457763672,
                                10.510000228881836,
                                10.90999984741211,
                                10.420000076293945,
                                10.3100004196167,
                                10.5,
                                10.5600004196167,
                                10.78499984741211,
                                10.760000228881836,
                                10.720000267028809,
                                11.079999923706055,
                                11.149999618530273,
                                11.675000190734863,
                                11.71500015258789,
                                11.755999565124512,
                                11.569999694824219,
                                11.699999809265137,
                                11.460000038146973,
                                11.16100025177002,
                                11.545000076293945,
                                11.789999961853027,
                                11.779999732971191,
                                11.729999542236328,
                                11.819999694824219,
                                11.550000190734863,
                                11.350000381469727,
                                11.380000114440918,
                                11.5,
                                11.619999885559082,
                                11.699999809265137,
                                11.760000228881836,
                                11.9399995803833,
                                11.949999809265137,
                                12.039999961853027,
                                12.050000190734863,
                                12.09000015258789,
                                12.050000190734863,
                                12.25,
                                12.220000267028809,
                                12.5,
                                12.979999542236328,
                                12.949999809265137,
                                12.84000015258789,
                                13.050000190734863,
                                12.949999809265137,
                                12.680000305175781,
                                12.640000343322754,
                                12.5,
                                12.59000015258789,
                                12.720000267028809,
                                12.680000305175781,
                                12.420000076293945,
                                12.449999809265137,
                                12.109999656677246,
                                12.180000305175781,
                                11.449999809265137,
                                11.609999656677246,
                                11.779999732971191,
                                11.869999885559082,
                                11.970000267028809,
                                11.539999961853027,
                                11.529999732971191,
                                11.399999618530273,
                                11.220000267028809,
                                11.239999771118164,
                                10.979999542236328,
                                11.050000190734863,
                                10.710000038146973,
                                10.40999984741211,
                                10.619999885559082,
                                10.4399995803833,
                                10.359999656677246,
                                10.289999961853027,
                                10.319999694824219,
                                10.420000076293945,
                                10.819999694824219,
                                10.850000381469727,
                                10.8100004196167,
                                10.529999732971191,
                                10.420000076293945,
                                10.079999923706055,
                                10.180000305175781,
                                9.930000305175781,
                                10.319999694824219,
                                10.289999961853027,
                                10.390000343322754,
                                10.369999885559082,
                                10.260000228881836,
                                10.260000228881836,
                                10.390000343322754,
                                10.510000228881836,
                                10.65999984741211,
                                10.489999771118164,
                                10.635000228881836,
                                10.390000343322754,
                                10.380000114440918,
                                10.4399995803833,
                                10.130000114440918,
                                9.859999656677246,
                                9.800000190734863,
                                9.824999809265137,
                                9.65999984741211,
                                10.119999885559082,
                                10.170000076293945,
                                9.649999618530273,
                                9.84000015258789,
                                9.819999694824219,
                                9.739999771118164,
                                9.779999732971191,
                                10.100000381469727,
                                9.90999984741211,
                                10.029999732971191,
                                10.1850004196167,
                                10.175000190734863,
                                10.109999656677246,
                                10.0600004196167,
                                10.220000267028809,
                                10.289999961853027,
                                10.5,
                                10.1850004196167,
                                10.192999839782715,
                                10.230999946594238,
                                10.25,
                                10.359999656677246
                            ]
                        }
                    ],
                    "adjclose": [
                        {
                            "adjclose": [
                                11.985328674316406,
                                11.90595531463623,
                                12.402036666870117,
                                12.392115592956543,
                                12.253212928771973,
                                12.114309310913086,
                                12.402036666870117,
                                12.054780006408691,
                                12.223447799682617,
                                12.153996467590332,
                                12.322664260864258,
                                12.402036666870117,
                                12.392115592956543,
                                12.471488952636719,
                                12.451645851135254,
                                12.550860404968262,
                                13.344592094421387,
                                13.880359649658203,
                                13.850595474243164,
                                13.850595474243164,
                                13.92004680633545,
                                13.840672492980957,
                                13.820830345153809,
                                13.126315116882324,
                                13.394200325012207,
                                13.166003227233887,
                                13.066786766052246,
                                13.662084579467773,
                                13.910126686096191,
                                14.237539291381836,
                                14.237539291381836,
                                14.386363983154297,
                                14.892366409301758,
                                14.614559173583984,
                                14.267303466796875,
                                13.92004680633545,
                                13.384278297424316,
                                13.146159172058105,
                                13.324748992919922,
                                12.92788314819336,
                                12.610391616821289,
                                12.044858932495117,
                                12.203604698181152,
                                12.322664260864258,
                                12.501254081726074,
                                12.550860404968262,
                                12.640155792236328,
                                13.046942710876465,
                                13.43388557434082,
                                13.870437622070312,
                                13.562867164611816,
                                13.324748992919922,
                                13.096550941467285,
                                12.967570304870605,
                                12.997334480285645,
                                12.640155792236328,
                                12.89811897277832,
                                13.046942710876465,
                                13.394200325012207,
                                13.195767402648926,
                                12.699686050415039,
                                12.62031364440918,
                                12.531018257141113,
                                12.153996467590332,
                                12.005172729492188,
                                11.925799369812012,
                                11.57854175567627,
                                11.618228912353516,
                                11.697602272033691,
                                11.985328674316406,
                                12.471488952636719,
                                12.600470542907715,
                                12.411958694458008,
                                12.560783386230469,
                                12.501254081726074,
                                12.451645851135254,
                                12.471488952636719,
                                12.402036666870117,
                                12.431802749633789,
                                12.114309310913086,
                                12.650077819824219,
                                13.205690383911133,
                                12.94772720336914,
                                12.719529151916504,
                                12.163918495178223,
                                12.511174201965332,
                                12.203604698181152,
                                12.382193565368652,
                                12.342507362365723,
                                11.816659927368164,
                                12.203604698181152,
                                12.064702033996582,
                                11.995251655578613,
                                11.90595531463623,
                                11.707523345947266,
                                12.104388236999512,
                                11.796817779541016,
                                11.608306884765625,
                                11.57854175567627,
                                11.737288475036621,
                                11.876191139221191,
                                12.124232292175293,
                                11.80673885345459,
                                12.015092849731445,
                                12.183760643005371,
                                12.183760643005371,
                                12.302821159362793,
                                12.302821159362793,
                                12.263134002685547,
                                12.074623107910156,
                                12.074623107910156,
                                12.025015830993652,
                                12.183760643005371,
                                12.282978057861328,
                                11.796817779541016,
                                11.290815353393555,
                                11.41979694366455,
                                11.469404220581055,
                                11.35034465789795,
                                11.300736427307129,
                                11.717446327209473,
                                11.608306884765625,
                                11.330501556396484,
                                11.697602272033691,
                                12.034936904907227,
                                11.757131576538086,
                                11.80673885345459,
                                12.124232292175293,
                                12.114309310913086,
                                11.995251655578613,
                                12.153996467590332,
                                12.005172729492188,
                                12.144074440002441,
                                12.064702033996582,
                                12.362351417541504,
                                12.094466209411621,
                                12.163918495178223,
                                11.251129150390625,
                                10.665752410888672,
                                10.774889945983887,
                                10.953479766845703,
                                11.112225532531738,
                                11.171754837036133,
                                11.320579528808594,
                                11.41979694366455,
                                11.092382431030273,
                                11.300736427307129,
                                11.39995288848877,
                                11.201519966125488,
                                11.132068634033203,
                                11.588464736938477,
                                11.598410606384277,
                                11.439255714416504,
                                11.389519691467285,
                                11.787406921386719,
                                11.926668167114258,
                                11.359678268432617,
                                11.488991737365723,
                                11.180628776550293,
                                11.210471153259277,
                                10.50422191619873,
                                10.185911178588867,
                                10.374908447265625,
                                10.852372169494629,
                                10.484326362609863,
                                10.832478523254395,
                                10.9319486618042,
                                10.534062385559082,
                                10.355012893676758,
                                10.50422191619873,
                                10.832478523254395,
                                11.20052433013916,
                                10.912055969238281,
                                11.061262130737305,
                                11.359678268432617,
                                11.797354698181152,
                                11.687934875488281,
                                11.996297836303711,
                                11.847090721130371,
                                11.687934875488281,
                                11.787406921386719,
                                11.439255714416504,
                                11.389519691467285,
                                11.866984367370605,
                                11.906773567199707,
                                11.847090721130371,
                                11.837141990661621,
                                11.847090721130371,
                                11.638199806213379,
                                11.469097137451172,
                                11.439255714416504,
                                11.628252029418945,
                                11.707829475402832,
                                11.767512321472168,
                                12.1256103515625,
                                11.946561813354492,
                                12.155452728271484,
                                12.165399551391602,
                                12.046032905578613,
                                12.075875282287598,
                                12.145505905151367,
                                12.304659843444824,
                                12.185295104980469,
                                13.329219818115234,
                                12.951227188110352,
                                13.020857810974121,
                                13.120328903198242,
                                13.329219818115234,
                                12.921385765075684,
                                12.722441673278809,
                                12.632917404174805,
                                12.622969627380371,
                                12.632917404174805,
                                12.942008972167969,
                                12.672800064086914,
                                12.433503150939941,
                                12.443472862243652,
                                12.283941268920898,
                                12.234087944030762,
                                11.685697555541992,
                                12.10446834564209,
                                11.8651704788208,
                                11.85520076751709,
                                11.974848747253418,
                                11.536136627197266,
                                11.635844230651855,
                                11.436429977416992,
                                11.396546363830566,
                                11.276898384094238,
                                10.997716903686523,
                                11.217073440551758,
                                10.678653717041016,
                                10.578946113586426,
                                10.668683052062988,
                                10.459297180175781,
                                10.578946113586426,
                                10.319707870483398,
                                10.48921012878418,
                                10.678653717041016,
                                11.017659187316895,
                                10.94786262512207,
                                10.848155975341797,
                                10.588916778564453,
                                10.419414520263672,
                                10.239941596984863,
                                10.210028648376465,
                                10.369560241699219,
                                10.299765586853027,
                                10.289794921875,
                                10.449326515197754,
                                10.399473190307617,
                                10.289794921875,
                                10.449326515197754,
                                10.568976402282715,
                                10.748448371887207,
                                10.628799438476562,
                                10.588916778564453,
                                10.778361320495605,
                                10.359590530395508,
                                10.449326515197754,
                                10.519122123718262,
                                10.100351333618164,
                                9.990674018859863,
                                9.970731735229492,
                                9.851082801818848,
                                9.691551208496094,
                                10.509151458740234,
                                10.24991226196289,
                                9.691551208496094,
                                9.970731735229492,
                                9.88099479675293,
                                9.94081974029541,
                                10.220000267028809,
                                10.110321998596191,
                                10.24991226196289,
                                10.160175323486328,
                                10.359590530395508,
                                10.220000267028809,
                                10.220000267028809,
                                10.229999542236328,
                                10.460000038146973,
                                10.550000190734863,
                                10.529999732971191,
                                10.239999771118164,
                                10.300000190734863,
                                10.300000190734863,
                                10.270000457763672,
                                10.609999656677246
                            ]
                        }
                    ]
                }
            }
        ],
        "error": null
    }
}